nautilusdb/__init__.py
nautilusdb/client/__init__.py
nautilusdb/client/admin_management.py
nautilusdb/client/collection_management.py
nautilusdb/client_models/__init__.py
nautilusdb/client_models/app.py
nautilusdb/client_models/collection.py
nautilusdb/client_models/collection_builder.py
nautilusdb/client_models/column_type.py
nautilusdb/client_models/vector.py
nautilusdb/server_models/__init__.py
nautilusdb/server_models/api.py
nautilusdb/server_models/app_api.py
nautilusdb/server_models/index.py
nautilusdb/server_models/unused.py
nautilusdb/tests/api_surface_test.py
nautilusdb/tests/smoke_test.py
nautilusdb/utils/__init__.py
nautilusdb/utils/config.py
nautilusdb/utils/exceptions.py
nautilusdb/utils/file_upload.py
nautilusdb-0.5.0.dist-info/METADATA
nautilusdb-0.5.0.dist-info/WHEEL
nautilusdb-0.5.0.dist-info/RECORD
